utilitime/__init__.py
utilitime/_version.py
utilitime/constants.py
utilitime/time_interval.py
utilitime/dateint/__init__.py
utilitime/dateint/dateint.py
utilitime/datetime/__init__.py
utilitime/datetime/datetime.py
utilitime/time/__init__.py
utilitime/time/time.py
utilitime/timestamp/__init__.py
utilitime/timestamp/timestamp.py
utilitime/weekday/__init__.py
utilitime/weekday/weekday.py
utilitime-0.0.3.dist-info/DESCRIPTION.rst
utilitime-0.0.3.dist-info/METADATA
utilitime-0.0.3.dist-info/RECORD
utilitime-0.0.3.dist-info/WHEEL
utilitime-0.0.3.dist-info/metadata.json
utilitime-0.0.3.dist-info/top_level.txt
