Metadata-Version: 2.0
Name: utilitime
Version: 0.0.3
Summary: A small pure-python package for time-related utility functions.
Home-page: https://github.com/shaypal5/utilitime
Author: Shay Palachy
Author-email: shaypal5@gmail.com
License: MIT
Keywords: python decorator decorators
Platform: any
Classifier: Development Status :: 4 - Beta
Classifier: License :: OSI Approved :: MIT License
Classifier: Programming Language :: Python
Classifier: Programming Language :: Python :: 3.5
Classifier: Programming Language :: Python :: 3.6
Classifier: Topic :: Software Development :: Libraries
Classifier: Topic :: Software Development :: Libraries :: Python Modules
Classifier: Intended Audience :: Developers
Requires-Dist: pytz
Requires-Dist: delorean
Requires-Dist: decore
Provides-Extra: test
Requires-Dist: pytest; extra == 'test'
Requires-Dist: coverage; extra == 'test'
Requires-Dist: pytest-cov; extra == 'test'
